LICENSE.txt
MANIFEST.in
README.md
setup.cfg
setup.py
mapr/__init__.py
mapr/ojai/__init__.py
mapr/ojai/document/MutationOp.py
mapr/ojai/document/MutationUtil.py
mapr/ojai/document/OJAIDocumentMutation.py
mapr/ojai/document/__init__.py
mapr/ojai/exceptions/AccessDeniedError.py
mapr/ojai/exceptions/ClusterNotFoundError.py
mapr/ojai/exceptions/ConditionNotClosedError.py
mapr/ojai/exceptions/ConnectionError.py
mapr/ojai/exceptions/ConnectionLostError.py
mapr/ojai/exceptions/DecodingError.py
mapr/ojai/exceptions/DocumentAlreadyExistsError.py
mapr/ojai/exceptions/DocumentMutationError.py
mapr/ojai/exceptions/DocumentNotFoundError.py
mapr/ojai/exceptions/EmptyConditionError.py
mapr/ojai/exceptions/EncodingError.py
mapr/ojai/exceptions/ExpiredTokenError.py
mapr/ojai/exceptions/FieldPathAlreadyInDocumentError.py
mapr/ojai/exceptions/GRPCError.py
mapr/ojai/exceptions/IORequestError.py
mapr/ojai/exceptions/IllegalArgumentError.py
mapr/ojai/exceptions/IllegalMutationError.py
mapr/ojai/exceptions/InvalidArgumentError.py
mapr/ojai/exceptions/InvalidOJAIDocumentError.py
mapr/ojai/exceptions/InvalidStreamResponseError.py
mapr/ojai/exceptions/PathNotFoundError.py
mapr/ojai/exceptions/QueryNotBuildError.py
mapr/ojai/exceptions/StoreAlreadyExistsError.py
mapr/ojai/exceptions/StoreNotFoundError.py
mapr/ojai/exceptions/UnknownPayloadEncodingError.py
mapr/ojai/exceptions/UnknownServerError.py
mapr/ojai/exceptions/UnrecognizedInsertModeError.py
mapr/ojai/exceptions/UnsupportedConstructorException.py
mapr/ojai/exceptions/__init__.py
mapr/ojai/ojai/OJAIDocument.py
mapr/ojai/ojai/OJAIDocumentStream.py
mapr/ojai/ojai/OJAIQueryResult.py
mapr/ojai/ojai/OJAITagsBuilder.py
mapr/ojai/ojai/__init__.py
mapr/ojai/ojai/document_utils.py
mapr/ojai/ojai_query/OJAIQuery.py
mapr/ojai/ojai_query/OJAIQueryCondition.py
mapr/ojai/ojai_query/QueryOp.py
mapr/ojai/ojai_query/__init__.py
mapr/ojai/ojai_utils/__init__.py
mapr/ojai/ojai_utils/ojai_dict.py
mapr/ojai/ojai_utils/ojai_document_creator.py
maprdb_python_client.egg-info/PKG-INFO
maprdb_python_client.egg-info/SOURCES.txt
maprdb_python_client.egg-info/dependency_links.txt
maprdb_python_client.egg-info/requires.txt
maprdb_python_client.egg-info/top_level.txt