Metadata-Version: 1.0
Name: maprdb-python-client
Version: 1.1.3
Summary: MapR-DB Python Client
Home-page: https://github.com/mapr/maprdb-python-client/
Author: MapR, Inc.
Author-email: UNKNOWN
License: UNKNOWN
Keywords: ojai python client mapr maprdb
Platform: UNKNOWN
